{
  "title": "Ready Set — Tasks Board",
  "subtitle": "Action items from the Dev Team Meetings on May 4, 2026 and May 11, 2026 — status as of May 11.",
  "generated": "2026-05-11",
  "sources": [
    "meetings/shared/2026-05-04-dev-team-meeting.md",
    "meetings/shared/2026-05-11-dev-team-meeting.md",
    "meetings/shared/2026-05-11-may4-action-item-review.md",
    "meetings/shared/2026-05-11-weekly-recap.md"
  ],
  "columns": [
    {
      "key": "done",
      "title": "✓ Done"
    },
    {
      "key": "progress",
      "title": "◐ In Progress / Blocked"
    },
    {
      "key": "open",
      "title": "○ Open (Carried Over)"
    },
    {
      "key": "new",
      "title": "★ New — May 11"
    }
  ],
  "owners": {
    "emmanuel": "Emmanuel",
    "gary": "Gary",
    "fernando": "Fernando"
  },
  "sourceLabels": {
    "may4": "May 4",
    "may11": "May 11",
    "qa": "QA",
    "catercow": "CaterCow"
  },
  "tasks": [
    {
      "id": "report-twilio-costs",
      "status": "done",
      "title": "Report Twilio costs (5-line analysis)",
      "owner": "fernando",
      "source": "may4",
      "sourceRef": "#9",
      "description": "5-line analysis delivered; fed into the larger counter-proposal."
    },
    {
      "id": "research-twilio-alternatives",
      "status": "done",
      "title": "Research alternative API providers vs Twilio",
      "owner": "emmanuel",
      "source": "may4",
      "sourceRef": "#10",
      "description": "Telnyx counter-proposal delivered — projected savings $780–$840/yr vs Twilio. SignalWire flagged as fallback. Report at <code>docs/ready-set/reports/2026-05-07-twilio-alternatives-analysis.md</code>."
    },
    {
      "id": "recruit-tester",
      "status": "done",
      "title": "Recruit tester (10–15 hrs/week)",
      "owner": "emmanuel",
      "source": "may4",
      "sourceRef": "#13",
      "description": "Candidate confirmed at ~15 hrs/week, communicated to Gary on 2026-05-06."
    },
    {
      "id": "work-50-hours",
      "status": "done",
      "title": "Work 50 hours this week (catch-up)",
      "owner": "fernando",
      "source": "may4",
      "sourceRef": "#12",
      "description": "Completed without flags raised in the recap."
    },
    {
      "id": "coolfire-bridge-api",
      "status": "progress",
      "title": "Internal Website → Google Sheet → Coolfire bridge API",
      "owner": "emmanuel",
      "source": "may4",
      "sourceRef": "#8",
      "tags": [
        "critical"
      ],
      "description": "Largest open item. Coolfire export still requires the Google Sheet hop until this lands. Blocks the July Coolfire sunset."
    },
    {
      "id": "driver-tracking-sync",
      "status": "progress",
      "title": "Resolve driver tracking sync issues",
      "owner": "emmanuel",
      "source": "may11",
      "description": "Status sync between dashboard ↔ driver interface + intermittent websocket connections. Prioritize distance calculations before map drawing."
    },
    {
      "id": "driver-phone-storage",
      "status": "progress",
      "title": "Decide driver phone storage (Sheet vs DB profile)",
      "owner": "emmanuel",
      "source": "may4",
      "sourceRef": "#1",
      "description": "Blocks the Google Sheet automation thread."
    },
    {
      "id": "coolfire-api-docs",
      "status": "open",
      "title": "Review Coolfire API docs & scope endpoints",
      "owner": "emmanuel",
      "source": "may4",
      "sourceRef": "#2",
      "description": "July transition target — clock is ticking."
    },
    {
      "id": "destino-square-integration",
      "status": "open",
      "title": "Integrate Destino via Square backend",
      "owner": "emmanuel",
      "source": "may4",
      "sourceRef": "#3",
      "description": "This week's Destino work was firefighting (stability/auth/deps), not the Square→ReadySet order API."
    },
    {
      "id": "fresh-rolls-review",
      "status": "open",
      "title": "Review Fresh Rolls site (Square-based)",
      "owner": "emmanuel",
      "source": "may4",
      "sourceRef": "#4",
      "description": "Inquiry from Gary; no proposal sent yet. They want to send and receive orders."
    },
    {
      "id": "consult-james-catercow",
      "status": "open",
      "title": "Consult James — Destino + existing CaterCow link?",
      "owner": "emmanuel",
      "source": "may4",
      "sourceRef": "#5",
      "description": "Gary planned to chat with him this week as well."
    },
    {
      "id": "princess-payment-reconcile",
      "status": "open",
      "title": "Reconcile Princess payment owed to Emmanuel",
      "owner": "gary",
      "source": "may4",
      "sourceRef": "#6",
      "description": "Outstanding small difference from previous work."
    },
    {
      "id": "legal-contract-nonpaying",
      "status": "open",
      "title": "Draft legal contract for non-paying clients",
      "owner": "gary",
      "source": "may4",
      "sourceRef": "#7",
      "description": "Tied to \"withhold maintenance, don't take down sites\" policy. Still needs paper."
    },
    {
      "id": "verify-twilio-region-isolation",
      "status": "open",
      "title": "Verify Twilio per-region isolation",
      "owner": "fernando",
      "source": "may4",
      "sourceRef": "#11",
      "tags": [
        "moot"
      ],
      "description": "Likely moot if Telnyx is approved; confirm equivalent in Telnyx evaluation instead."
    },
    {
      "id": "rea-342-soft-delete-orders",
      "status": "open",
      "title": "REA-342 — Fix hard-delete in /api/orders/delete",
      "owner": "emmanuel",
      "source": "qa",
      "sourceRef": "REA-342",
      "relatedQa": "REA-OMG-06",
      "tags": [
        "bug"
      ],
      "description": "DELETE /api/orders/delete performs hard delete instead of soft-delete. Schema gaps: <code>Dispatch.deletedAt</code> and <code>deletedBy</code> missing. Promoted from QA fail on test REA-OMG-06."
    },
    {
      "id": "rea-343-bulk-delete-defects",
      "status": "open",
      "title": "REA-343 — Fix bulk-delete defects + S3 cleanup",
      "owner": "emmanuel",
      "source": "qa",
      "sourceRef": "REA-343",
      "relatedQa": "REA-OMG-07",
      "tags": [
        "bug"
      ],
      "description": "6 defects in <code>src/app/api/orders/bulk-delete/route.ts</code>: hard delete instead of soft, wrong S3 bucket name, BUCKET_NAME shadowed, path extraction fallback orphans files, storage errors swallowed, no orphan tracking. Promoted from QA fail on test REA-OMG-07."
    },
    {
      "id": "rea-344-assign-driver-broadcast",
      "status": "open",
      "title": "REA-344 — Wire assignDriver realtime broadcast",
      "owner": "emmanuel",
      "source": "qa",
      "sourceRef": "REA-344",
      "relatedQa": "REA-OMG-08",
      "tags": [
        "bug"
      ],
      "description": "No realtime broadcast emitted from <code>assignDriver/route.ts</code>. Infrastructure exists (<code>broadcastDeliveryAssigned</code> in <code>lib/realtime/channels.ts:475</code>) but has zero callers — admin dashboard requires reload. Secondary: Delivery upsert creates rows with <code>deliveryAddress=''</code> and swallows errors. Promoted from QA fail on test REA-OMG-08."
    },
    {
      "id": "rea-drt-07-supabase-browser-session-bridge",
      "status": "open",
      "title": "REA-DRT-07 — Bridge SSR cookie to browser supabase-js session (Realtime never initializes)",
      "owner": "emmanuel",
      "source": "qa",
      "relatedQa": "REA-DRT-07",
      "tags": [
        "bug",
        "critical"
      ],
      "description": "<code>supabase.auth.getSession()</code> returns null in the browser; <code>localStorage</code> has no <code>sb-&lt;ref&gt;-auth-token</code> key after login. SSR cookie is set server-side but not bridged to the browser <code>supabase-js</code> client, so all Realtime-dependent flows (<code>useRealtimeLocationTracking</code>, <code>useAdminRealtimeTracking</code>) early-return and never open a WS connection. <strong>First investigation target:</strong> <code>src/utils/supabase/client.ts</code> vs <code>src/middleware.ts</code> — verify <code>createBrowserClient</code> cookie config matches the SSR client. Related: Sentry READY-SET-NEXTJS-1S (unhandled refresh rejection on <code>/driver/tracking</code> — patched on <code>fix/auth-refresh-unhandled-rejection</code> as graceful failure, but root cause is this bug). Reported by Fer in QA notes; no engineering ticket filed yet."
    },
    {
      "id": "test-telnyx-integration",
      "status": "new",
      "title": "Test Telnyx Integration",
      "owner": "emmanuel",
      "source": "may11",
      "description": "Verify the new vendor works correctly with the existing codebase."
    },
    {
      "id": "email-telnyx-details",
      "status": "new",
      "title": "Email Telnyx provider details",
      "owner": "emmanuel",
      "source": "may11",
      "description": "Send Gary the information regarding the alternative telecom vendor Telnyx."
    },
    {
      "id": "calc-porting-costs",
      "status": "new",
      "title": "Calculate 5-line porting/migration costs",
      "owner": "emmanuel",
      "source": "may11",
      "description": "Determine the total fee required for porting 5 lines to the new platform."
    },
    {
      "id": "research-phone-segmentation",
      "status": "new",
      "title": "Research phone segmentation by marketplace",
      "owner": "emmanuel",
      "source": "may11",
      "description": "Investigate groups/dividers to organize marketplaces inside the comms provider. Goal: consolidate 5 lines → 3."
    },
    {
      "id": "update-hours-sheet",
      "status": "new",
      "title": "Update Hours Sheet (previous weeks)",
      "owner": "emmanuel",
      "source": "may11",
      "description": "Record the work duration from the previous weeks into the tracking document."
    },
    {
      "id": "contact-james-trial",
      "status": "new",
      "title": "Contact James — order processing trial",
      "owner": "gary",
      "source": "may11",
      "description": "Reach out this week to coordinate a trial for order processing using the new integration. James is the pilot client."
    },
    {
      "id": "james-payment-plan",
      "status": "new",
      "title": "Create payment plan for James",
      "owner": "gary",
      "source": "may11",
      "description": "Establish a schedule for James to pay outstanding invoices — funds additional testing resources."
    },
    {
      "id": "kco-calculator-scope",
      "status": "new",
      "title": "Calculator scope for KCO integration",
      "owner": "emmanuel",
      "source": "may11",
      "description": "Calculator must handle driver, vendor, and internal calculations simultaneously to eliminate manual data entry errors."
    },
    {
      "id": "catercow-webhook-preconfigure",
      "status": "progress",
      "title": "Pre-configure CaterCow staging webhook URL",
      "owner": "emmanuel",
      "source": "catercow",
      "description": "Dispatcher landed (<code>src/lib/services/partnerWebhookService.ts</code>) and wired into the status route; <code>scripts/update-partner-webhook.ts</code> is ready. Still need to run it against the staging DB: <code>PARTNER_SLUG=catercow WEBHOOK_URL=https://api.staging.steerdelivery.com/webhooks/ready_set pnpm tsx scripts/update-partner-webhook.ts</code>. Their endpoint isn't live yet, so dispatcher will log <code>[partner-webhook] misconfigured</code> until <code>webhookSecret</code> is also set."
    },
    {
      "id": "catercow-dispatcher-refactor",
      "status": "done",
      "title": "Generalize outbound webhook dispatcher (partner-registry-driven)",
      "owner": "emmanuel",
      "source": "catercow",
      "description": "New <code>src/lib/services/partnerWebhookService.ts</code> reads <code>webhookUrl</code>/<code>webhookSecret</code> from the <code>api_partners</code> row at send time. Wired into <code>/api/catering-requests/[orderId]/status/route.ts</code> for partners not in <code>CARRIER_CONFIGS</code>. HMAC-SHA256 signed per <code>API_CONTRACT.md</code> (<code>x-readyset-signature</code>); 3-attempt retry, no-retry on 4xx; 6 new unit tests; existing 161 cater-valley tests still green."
    },
    {
      "id": "catercow-hmac-secret",
      "status": "new",
      "title": "Generate + deliver CaterCow webhook HMAC secret",
      "owner": "emmanuel",
      "source": "catercow",
      "description": "Generate a 256-bit secret (<code>crypto.randomBytes(32)</code>), set <code>webhookSecret</code> on the staging row, deliver to CaterCow via 1Password share link (7-day expiry). Trigger: their webhook endpoint becomes reachable."
    },
    {
      "id": "catercow-steerdelivery-domain-check",
      "status": "new",
      "title": "Confirm CaterCow ↔ steerdelivery.com relationship with Gary",
      "owner": "emmanuel",
      "source": "catercow",
      "description": "Nate's webhook URL is on <code>steerdelivery.com</code>, not <code>catercow.com</code>. Verify this is a known parent/shared-infra relationship before exchanging production HMAC secrets. Quick Slack to Gary should resolve."
    },
    {
      "id": "catercow-get-orders-scope",
      "status": "open",
      "title": "Scope GET /orders/{id} for partner API v1.x",
      "owner": "emmanuel",
      "source": "catercow",
      "description": "Pre-scoped in <code>docs/catercow/IMPLEMENTATION_PLAN.md</code> Phase 4.1 (~half day). Reads from <code>catering_requests</code> filtered by <code>brokerage = partner.displayName</code>, returns status + last 10 lifecycle events. Pull forward only if CaterCow flags as a go-live blocker."
    },
    {
      "id": "catercow-openapi-export",
      "status": "open",
      "title": "OpenAPI 3.1 export from Zod schemas",
      "owner": "emmanuel",
      "source": "catercow",
      "description": "Pre-scoped in <code>docs/catercow/IMPLEMENTATION_PLAN.md</code> Phase 4.2 (~half day). Generate from existing Zod schemas in <code>src/app/api/partners/orders/*/route.ts</code> using <code>zod-to-openapi</code>; output <code>docs/catercow/openapi.yaml</code> + a <code>pnpm openapi:partners</code> script. Defer until CaterCow flags it as needed."
    }
  ]
}
